amazon_sp_api_clients/__init__.py
amazon_sp_api_clients/aplus_content_2020_11_01.py
amazon_sp_api_clients/authorization_v1.py
amazon_sp_api_clients/base.py
amazon_sp_api_clients/cache.py
amazon_sp_api_clients/catalog_items_2020_12_01.py
amazon_sp_api_clients/catalog_items_2022_04_01.py
amazon_sp_api_clients/catalog_items_v0.py
amazon_sp_api_clients/data_kiosk_2023_11_15.py
amazon_sp_api_clients/fba_inbound_eligibility_v1.py
amazon_sp_api_clients/fba_inventory_v1.py
amazon_sp_api_clients/fba_small_and_light_v1.py
amazon_sp_api_clients/feed_types.py
amazon_sp_api_clients/feeds_2020_09_04.py
amazon_sp_api_clients/feeds_2021_06_30.py
amazon_sp_api_clients/finances_v0.py
amazon_sp_api_clients/fulfillment_inbound_v0.py
amazon_sp_api_clients/fulfillment_outbound_2020_07_01.py
amazon_sp_api_clients/listings_items_2020_09_01.py
amazon_sp_api_clients/listings_items_2021_08_01.py
amazon_sp_api_clients/listings_restrictions_2021_08_01.py
amazon_sp_api_clients/marketplaces.py
amazon_sp_api_clients/merchant_fulfillment_v0.py
amazon_sp_api_clients/messaging_v1.py
amazon_sp_api_clients/notifications_v1.py
amazon_sp_api_clients/orders_v0.py
amazon_sp_api_clients/product_fees_v0.py
amazon_sp_api_clients/product_pricing_2022_05_01.py
amazon_sp_api_clients/product_pricing_v0.py
amazon_sp_api_clients/product_type_definitions_2020_09_01.py
amazon_sp_api_clients/replenishment_2022_11_07.py
amazon_sp_api_clients/report_types.py
amazon_sp_api_clients/reports_2020_09_04.py
amazon_sp_api_clients/reports_2021_06_30.py
amazon_sp_api_clients/sales_v1.py
amazon_sp_api_clients/sellers_v1.py
amazon_sp_api_clients/services_v1.py
amazon_sp_api_clients/shipment_invoicing_v0.py
amazon_sp_api_clients/shipping_v1.py
amazon_sp_api_clients/solicitations_v1.py
amazon_sp_api_clients/supply_sources_2020_07_01.py
amazon_sp_api_clients/tokens_2021_03_01.py
amazon_sp_api_clients/uploads_2020_11_01.py
amazon_sp_api_clients/vendor_direct_fulfillment_inventory_v1.py
amazon_sp_api_clients-1.9.2.dist-info/METADATA
amazon_sp_api_clients-1.9.2.dist-info/WHEEL
amazon_sp_api_clients-1.9.2.dist-info/RECORD
