Metadata-Version: 2.1
Name: amazon-sp-api-clients
Version: 1.9.2
Summary: Amazon selling partner api clients.
License: MIT
Author: Haoyu Pan
Author-email: panhaoyu.china@outlook.com
Requires-Python: >=3.7,<4.0
Classifier: License :: OSI Approved :: MIT License
Classifier: Operating System :: OS Independent
Classifier: Programming Language :: Python :: 3
Classifier: Programming Language :: Python :: 3.7
Classifier: Programming Language :: Python :: 3.8
Classifier: Programming Language :: Python :: 3.9
Classifier: Programming Language :: Python :: 3.10
Classifier: Programming Language :: Python :: 3.11
Requires-Dist: boto3 (>=1.28.45,<2.0.0)
Requires-Dist: cachetools (>=5.3.1,<6.0.0)
Requires-Dist: chardet (>=5.2.0,<6.0.0)
Requires-Dist: demjson3 (>=3.0.6,<4.0.0)
Requires-Dist: peewee (>=3.16.3,<4.0.0)
Requires-Dist: pycryptodome (>=3.18.0,<4.0.0)
Requires-Dist: requests (>=2.31.0,<3.0.0)
Project-URL: repository, https://github.com/panhaoyu/sp-api-clients
